SAMTEST/__init__.py
SAMTEST/_queen.py
SAMTEST/caltest.py
SAMTEST-2.1.0.dist-info/METADATA
SAMTEST-2.1.0.dist-info/WHEEL
SAMTEST-2.1.0.dist-info/top_level.txt
SAMTEST-2.1.0.dist-info/RECORD
