Metadata-Version: 2.1
Name: SAMTEST
Version: 2.1.0
Summary: A simple library for demonstrating how to share a Python package
Home-page: UNKNOWN
Author: UNKNOWN
Author-email: UNKNOWN
License: UNKNOWN
Platform: UNKNOWN
